PythonShujuKexueHeJiqiXuexiShijianZhinanChuyi/README.md
PythonShujuKexueHeJiqiXuexiShijianZhinanChuyi/__init__.py
PythonShujuKexueHeJiqiXuexiShijianZhinanChuyi/__main__.py
PythonShujuKexueHeJiqiXuexiShijianZhinanChuyi/file.epub
PythonShujuKexueHeJiqiXuexiShijianZhinanChuyi/index.html
PythonShujuKexueHeJiqiXuexiShijianZhinanChuyi/css/__init__.py
PythonShujuKexueHeJiqiXuexiShijianZhinanChuyi/css/annotations.css
PythonShujuKexueHeJiqiXuexiShijianZhinanChuyi/css/main.css
PythonShujuKexueHeJiqiXuexiShijianZhinanChuyi/css/normalize.css
PythonShujuKexueHeJiqiXuexiShijianZhinanChuyi/css/popup.css
PythonShujuKexueHeJiqiXuexiShijianZhinanChuyi/font/__init__.py
PythonShujuKexueHeJiqiXuexiShijianZhinanChuyi/font/fontello.eot
PythonShujuKexueHeJiqiXuexiShijianZhinanChuyi/font/fontello.svg
PythonShujuKexueHeJiqiXuexiShijianZhinanChuyi/font/fontello.ttf
PythonShujuKexueHeJiqiXuexiShijianZhinanChuyi/font/fontello.woff
PythonShujuKexueHeJiqiXuexiShijianZhinanChuyi/img/__init__.py
PythonShujuKexueHeJiqiXuexiShijianZhinanChuyi/img/annotator-glyph-sprite.png
PythonShujuKexueHeJiqiXuexiShijianZhinanChuyi/img/annotator-icon-sprite.png
PythonShujuKexueHeJiqiXuexiShijianZhinanChuyi/img/apple-touch-icon.png
PythonShujuKexueHeJiqiXuexiShijianZhinanChuyi/img/cancelfullscreen.png
PythonShujuKexueHeJiqiXuexiShijianZhinanChuyi/img/close.png
PythonShujuKexueHeJiqiXuexiShijianZhinanChuyi/img/fullscreen.png
PythonShujuKexueHeJiqiXuexiShijianZhinanChuyi/img/loader.gif
PythonShujuKexueHeJiqiXuexiShijianZhinanChuyi/img/menu-icon.png
PythonShujuKexueHeJiqiXuexiShijianZhinanChuyi/img/save.png
PythonShujuKexueHeJiqiXuexiShijianZhinanChuyi/img/saved.png
PythonShujuKexueHeJiqiXuexiShijianZhinanChuyi/img/settings-s.png
PythonShujuKexueHeJiqiXuexiShijianZhinanChuyi/img/settings.png
PythonShujuKexueHeJiqiXuexiShijianZhinanChuyi/img/star.png
PythonShujuKexueHeJiqiXuexiShijianZhinanChuyi/js/__init__.py
PythonShujuKexueHeJiqiXuexiShijianZhinanChuyi/js/epub.js
python_shuju_kexue_he_jiqi_xuexi_shijian_zhinan_chuyi-2024.3.6.0.dist-info/METADATA
python_shuju_kexue_he_jiqi_xuexi_shijian_zhinan_chuyi-2024.3.6.0.dist-info/WHEEL
python_shuju_kexue_he_jiqi_xuexi_shijian_zhinan_chuyi-2024.3.6.0.dist-info/entry_points.txt
python_shuju_kexue_he_jiqi_xuexi_shijian_zhinan_chuyi-2024.3.6.0.dist-info/top_level.txt
python_shuju_kexue_he_jiqi_xuexi_shijian_zhinan_chuyi-2024.3.6.0.dist-info/RECORD
